mkdocs_autodoc/__init__.py
mkdocs_autodoc/build.py
mkdocs_autodoc/config.py
mkdocs_autodoc/nav.py
mkdocs_autodoc/themes/bootstrap/_details.html
mkdocs_autodoc/themes/bootstrap/_summary.html
mkdocs_autodoc/themes/bootstrap/class.html
mkdocs_autodoc/themes/bootstrap/module.html
mkdocs_autodoc/themes/markdown/_details.md
mkdocs_autodoc/themes/markdown/_summary.md
mkdocs_autodoc/themes/markdown/class.md
mkdocs_autodoc/themes/markdown/module.md
mkdocs_autodoc/themes/mkdocs/_details.html
mkdocs_autodoc/themes/mkdocs/_summary.html
mkdocs_autodoc/themes/mkdocs/class.html
mkdocs_autodoc/themes/mkdocs/module.html
mkdocs_autodoc/themes/readthedocs/_details.html
mkdocs_autodoc/themes/readthedocs/_summary.html
mkdocs_autodoc/themes/readthedocs/class.html
mkdocs_autodoc/themes/readthedocs/module.html
mkdocs_autodoc-1.0.3.dist-info/DESCRIPTION.rst
mkdocs_autodoc-1.0.3.dist-info/METADATA
mkdocs_autodoc-1.0.3.dist-info/metadata.json
mkdocs_autodoc-1.0.3.dist-info/RECORD
mkdocs_autodoc-1.0.3.dist-info/top_level.txt
mkdocs_autodoc-1.0.3.dist-info/WHEEL
