Metadata-Version: 2.0
Name: mkdocs-autodoc
Version: 1.0.3
Summary: Auto-documentation for python modules for the mkdocs documentation system.
Home-page: https://github.com/erichulser/mkdocs_autodoc
Author: Eric Hulser
Author-email: eric.hulser@projexsoftware.com
License: LGPL
Platform: UNKNOWN
Requires-Dist: mkdocs
Requires-Dist: projex
